{
  "name": { "fr": "Citronnelle", "en": "Lemongrass" },
  "scientific": "Cymbopogon citratus",
  "description": {
    "fr": "Une longue tige fibreuse qui libère un citron clair et lumineux, idéal pour rafraîchir l'esprit après la touffeur du jour.",
    "en": "A long fibrous stalk that releases a clear, luminous lemon — perfect for cooling the mind after a sticky afternoon."
  },
  "benefits": ["digestion", "refresh", "stress"],
  "primaryBenefits": ["refresh"],
  "flavor": {
    "fr": ["citron", "vif", "vert"],
    "en": ["lemony", "bright", "green"]
  },
  "part": "leaves",
  "brewing": { "temperatureC": 95, "timeMin": 7, "gramsPerCup": 2 },
  "emoji": "🌾",
  "popularity": 75
}
